DIRACCommon/__init__.py
DIRACCommon/ConfigurationSystem/__init__.py
DIRACCommon/ConfigurationSystem/Client/__init__.py
DIRACCommon/ConfigurationSystem/Client/Helpers/Resources.py
DIRACCommon/ConfigurationSystem/Client/Helpers/__init__.py
DIRACCommon/Core/__init__.py
DIRACCommon/Core/Utilities/DErrno.py
DIRACCommon/Core/Utilities/JDL.py
DIRACCommon/Core/Utilities/List.py
DIRACCommon/Core/Utilities/ReturnValues.py
DIRACCommon/Core/Utilities/StateMachine.py
DIRACCommon/Core/Utilities/TimeUtilities.py
DIRACCommon/Core/Utilities/__init__.py
DIRACCommon/Core/Utilities/ClassAd/ClassAdLight.py
DIRACCommon/Core/Utilities/ClassAd/__init__.py
DIRACCommon/WorkloadManagementSystem/__init__.py
DIRACCommon/WorkloadManagementSystem/Client/JobStatus.py
DIRACCommon/WorkloadManagementSystem/Client/__init__.py
DIRACCommon/WorkloadManagementSystem/Client/JobState/JobManifest.py
DIRACCommon/WorkloadManagementSystem/Client/JobState/__init__.py
DIRACCommon/WorkloadManagementSystem/DB/JobDBUtils.py
DIRACCommon/WorkloadManagementSystem/DB/__init__.py
DIRACCommon/WorkloadManagementSystem/Utilities/JobModel.py
DIRACCommon/WorkloadManagementSystem/Utilities/JobStatusUtility.py
DIRACCommon/WorkloadManagementSystem/Utilities/ParametricJob.py
DIRACCommon/WorkloadManagementSystem/Utilities/__init__.py
diraccommon-9.0.16.dist-info/METADATA
diraccommon-9.0.16.dist-info/WHEEL
diraccommon-9.0.16.dist-info/RECORD
