Metadata-Version: 2.4
Name: DIRACCommon
Version: 9.0.16
Summary: Stateless utilities extracted from DIRAC for use by DiracX and other projects
Project-URL: Homepage, https://github.com/DIRACGrid/DIRAC
Project-URL: Documentation, https://dirac.readthedocs.io/
Project-URL: Source Code, https://github.com/DIRACGrid/DIRAC
Author-email: DIRAC Collaboration <dirac-dev@cern.ch>
License: GPL-3.0-only
Classifier: Development Status :: 5 - Production/Stable
Classifier: Intended Audience :: Science/Research
Classifier: License :: OSI Approved :: GNU General Public License v3 (GPLv3)
Classifier: Programming Language :: Python :: 3
Classifier: Topic :: Scientific/Engineering
Classifier: Topic :: System :: Distributed Computing
Requires-Python: >=3.11
Requires-Dist: diraccfg
Requires-Dist: pydantic>=2.0.0
Requires-Dist: typing-extensions>=4.0.0
Provides-Extra: testing
Requires-Dist: pytest-cov>=4.0.0; extra == 'testing'
Requires-Dist: pytest>=7.0.0; extra == 'testing'
